redis_proxyip_client/__about__.py
redis_proxyip_client/__init__.py
redis_proxyip_client/client.py
redis_proxyip_client/excep.py
redis_proxyip_client/third_party.py
redis_proxyip_client/config/__init__.py
redis_proxyip_client/config/default_config.py
redis_proxyip_client-0.3.0.dist-info/LICENSE
redis_proxyip_client-0.3.0.dist-info/METADATA
redis_proxyip_client-0.3.0.dist-info/WHEEL
redis_proxyip_client-0.3.0.dist-info/top_level.txt
redis_proxyip_client-0.3.0.dist-info/RECORD
