Metadata-Version: 2.1
Name: redis-proxyip-client
Version: 0.3.0
Summary: Python Proxyip Client backed with Redis Storage.
Home-page: https://github.com/Gatsby-Lee/redis-proxyip-pyclient
Author: Gatsby Lee
License: GPL-3.0
Keywords: redis retry failure
Platform: UNKNOWN
Classifier: Development Status :: 5 - Production/Stable
Classifier: Intended Audience :: Developers
Classifier: License :: OSI Approved :: GNU General Public License v3 (GPLv3)
Classifier: Programming Language :: Python
Classifier: Programming Language :: Python :: 3
Classifier: Programming Language :: Python :: 3.6
Classifier: Programming Language :: Python :: 3.7
Classifier: Topic :: Utilities
Requires-Python: >=3.6
Requires-Dist: be-proxy-ip
Requires-Dist: retry-redis
Provides-Extra: dev
Requires-Dist: pytest ; extra == 'dev'
Requires-Dist: pytest-mock ; extra == 'dev'
Requires-Dist: wheel ; extra == 'dev'
Requires-Dist: bpython ; extra == 'dev'
Requires-Dist: flake8 ; extra == 'dev'
Requires-Dist: autopep8 ; extra == 'dev'
Requires-Dist: pylint ; extra == 'dev'
Provides-Extra: test
Requires-Dist: pytest ; extra == 'test'
Requires-Dist: pytest-mock ; extra == 'test'
